main.py
setup.py
x2vml_gml.egg-info/PKG-INFO
x2vml_gml.egg-info/SOURCES.txt
x2vml_gml.egg-info/dependency_links.txt
x2vml_gml.egg-info/requires.txt
x2vml_gml.egg-info/top_level.txt